{
    "version": "3,0",
    "fps": 30.0,
    "scene": {
        "timestamp": 0.0447905,
        "actors": [
            {
                "name": "Puppeteer",
                "color": [
                    107,
                    178,
                    164
                ],
                "meta": {
                    "hasGloves": True,
                    "hasLeftGlove": True,
                    "hasRightGlove": False,
                    "hasBody": False,
                    "hasFace": False
                },
                "dimensions": {
                    "totalHeight": 1.69,
                    "hipHeight": 0.897514164
                },
                "body": {
                    "hip": {
                        "position": {
                            "x": 0.0,
                            "y": 0.897514164,
                            "z": 1.19511242e-07
                        },
                        "rotation": {
                            "x": 0.0,
                            "y": 0.0,
                            "z": 0.0,
                            "w": 1.0
                        }
                    },
                    "spine": {
                        "position": {
                            "x": -2.971742e-07,
                            "y": 0.978518546,
                            "z": -0.0376982875
                        },
                        "rotation": {
                            "x": -1.05221391e-23,
                            "y": 1.71839559e-07,
                            "z": 1.0,
                            "w": 6.123234e-17
                        }
                    },
                    "chest": {
                        "position": {
                            "x": 4.209511e-08,
                            "y": 1.24594128,
                            "z": -0.03769854
                        },
                        "rotation": {
                            "x": -1.05221391e-23,
                            "y": 1.71839559e-07,
                            "z": 1.0,
                            "w": 6.123234e-17
                        }
                    },
                    "neck": {
                        "position": {
                            "x": 8.200672e-08,
                            "y": 1.43943882,
                            "z": -0.037699
                        },
                        "rotation": {
                            "x": -3.57752641e-24,
                            "y": 5.84254423e-08,
                            "z": 1.0,
                            "w": 6.123234e-17
                        }
                    },
                    "head": {
                        "position": {
                            "x": 1.906482e-07,
                            "y": 1.54432,
                            "z": -0.03769898
                        },
                        "rotation": {
                            "x": 4.9924524e-31,
                            "y": 0.0,
                            "z": 1.0,
                            "w": 6.123234e-17
                        }
                    },
                    "leftShoulder": {
                        "position": {
                            "x": -0.06721877,
                            "y": 1.36470807,
                            "z": -0.0194170438
                        },
                        "rotation": {
                            "x": -0.09229583,
                            "y": 0.09229607,
                            "z": 0.7010574,
                            "w": -0.7010574
                        }
                    },
                    "leftUpperArm": {
                        "position": {
                            "x": -0.1913554,
                            "y": 1.36470807,
                            "z": -0.05267935
                        },
                        "rotation": {
                            "x": -0.04803672,
                            "y": 0.694637,
                            "z": -0.180697262,
                            "w": 0.694637
                        }
                    },
                    "leftLowerArm": {
                        "position": {
                            "x": -0.237283871,
                            "y": 1.13292813,
                            "z": 0.0265119411
                        },
                        "rotation": {
                            "x": -0.0232116226,
                            "y": -0.390482426,
                            "z": 0.8855706,
                            "w": -0.2504993
                        }
                    },
                    "leftHand": {
                        "position": {
                            "x": -0.364006579,
                            "y": 1.28921819,
                            "z": 0.213103414
                        },
                        "rotation": {
                            "x": -0.232276246,
                            "y": -0.380415678,
                            "z": 0.702057838,
                            "w": -0.555379868
                        }
                    },
                    "rightShoulder": {
                        "position": {
                            "x": 0.06721889,
                            "y": 1.36470807,
                            "z": -0.0194171723
                        },
                        "rotation": {
                            "x": 0.09229583,
                            "y": 0.09229607,
                            "z": 0.7010574,
                            "w": 0.7010574
                        }
                    },
                    "rightUpperArm": {
                        "position": {
                            "x": 0.191355556,
                            "y": 1.36470807,
                            "z": -0.0526793748
                        },
                        "rotation": {
                            "x": 0.0137464758,
                            "y": -0.675450265,
                            "z": -0.0178620033,
                            "w": 0.737060845
                        }
                    },
                    "rightLowerArm": {
                        "position": {
                            "x": 0.189421132,
                            "y": 1.11575723,
                            "z": -0.06374233
                        },
                        "rotation": {
                            "x": -0.0157293361,
                            "y": -0.675406933,
                            "z": 0.0143051408,
                            "w": 0.73713845
                        }
                    },
                    "rightHand": {
                        "position": {
                            "x": 0.189377382,
                            "y": 0.8415945,
                            "z": -0.052076716
                        },
                        "rotation": {
                            "x": -0.0157293361,
                            "y": -0.675406933,
                            "z": 0.0143051408,
                            "w": 0.73713845
                        }
                    },
                    "leftUpLeg": {
                        "position": {
                            "x": -0.0773389861,
                            "y": 0.897514164,
                            "z": 1.19511242e-07
                        },
                        "rotation": {
                            "x": -0.00617059227,
                            "y": 0.7070798,
                            "z": 0.00617059227,
                            "w": 0.7070798
                        }
                    },
                    "leftLeg": {
                        "position": {
                            "x": -0.07014018,
                            "y": 0.485102445,
                            "z": 2.87966827e-07
                        },
                        "rotation": {
                            "x": 0.02467767,
                            "y": 0.706675947,
                            "z": 0.03700711,
                            "w": 0.706137657
                        }
                    },
                    "leftFoot": {
                        "position": {
                            "x": -0.0635496,
                            "y": 0.07329887,
                            "z": -0.03603228
                        },
                        "rotation": {
                            "x": 0.0308436323,
                            "y": 0.7064337,
                            "z": -0.7064337,
                            "w": 0.0308435857
                        }
                    },
                    "leftToe": {
                        "position": {
                            "x": -0.07450858,
                            "y": 0.0137245692,
                            "z": 0.08923096
                        },
                        "rotation": {
                            "x": 0.0308435652,
                            "y": 0.706433833,
                            "z": -0.7064336,
                            "w": 0.0308436565
                        }
                    },
                    "leftToeEnd": {
                        "position": {
                            "x": -0.07450858,
                            "y": 0.0137245692,
                            "z": 0.08923096
                        },
                        "rotation": {
                            "x": 0.0308435652,
                            "y": 0.706433833,
                            "z": -0.7064336,
                            "w": 0.0308436565
                        }
                    },
                    "rightUpLeg": {
                        "position": {
                            "x": 0.0773389861,
                            "y": 0.897514164,
                            "z": 1.17234805e-07
                        },
                        "rotation": {
                            "x": -0.00617059227,
                            "y": -0.7070798,
                            "z": -0.00617059227,
                            "w": 0.7070798
                        }
                    },
                    "rightLeg": {
                        "position": {
                            "x": 0.0701402649,
                            "y": 0.485102355,
                            "z": 2.81137432e-07
                        },
                        "rotation": {
                            "x": 0.02467767,
                            "y": -0.706675947,
                            "z": -0.03700711,
                            "w": 0.706137657
                        }
                    },
                    "rightFoot": {
                        "position": {
                            "x": 0.06354957,
                            "y": 0.07329881,
                            "z": -0.03603233
                        },
                        "rotation": {
                            "x": -0.0308436323,
                            "y": 0.7064337,
                            "z": -0.7064337,
                            "w": -0.0308435857
                        }
                    },
                    "rightToe": {
                        "position": {
                            "x": 0.07450868,
                            "y": 0.0137244835,
                            "z": 0.08923091
                        },
                        "rotation": {
                            "x": -0.0308436323,
                            "y": 0.7064337,
                            "z": -0.7064337,
                            "w": -0.0308435857
                        }
                    },
                    "rightToeEnd": {
                        "position": {
                            "x": 0.07450868,
                            "y": 0.0137244835,
                            "z": 0.08923091
                        },
                        "rotation": {
                            "x": -0.0308436323,
                            "y": 0.7064337,
                            "z": -0.7064337,
                            "w": -0.0308435857
                        }
                    },
                    "leftThumbProximal": {
                        "position": {
                            "x": -0.375675946,
                            "y": 1.30648708,
                            "z": 0.239314839
                        },
                        "rotation": {
                            "x": -0.381113768,
                            "y": -0.8567219,
                            "z": 0.2609552,
                            "w": 0.229525879
                        }
                    },
                    "leftThumbMedial": {
                        "position": {
                            "x": -0.396016836,
                            "y": 1.284617,
                            "z": 0.263045371
                        },
                        "rotation": {
                            "x": 0.553892851,
                            "y": 0.829879045,
                            "z": 0.0446324125,
                            "w": 0.05011924
                        }
                    },
                    "leftThumbDistal": {
                        "position": {
                            "x": -0.422505736,
                            "y": 1.27354407,
                            "z": 0.25929296
                        },
                        "rotation": {
                            "x": 0.5183344,
                            "y": 0.7850406,
                            "z": 0.272768319,
                            "w": 0.20159024
                        }
                    },
                    "leftThumbTip": {
                        "position": {
                            "x": -0.44578746,
                            "y": 1.26316249,
                            "z": 0.238214523
                        },
                        "rotation": {
                            "x": 0.5183346,
                            "y": 0.785041749,
                            "z": 0.272765875,
                            "w": 0.201588526
                        }
                    },
                    "leftIndexProximal": {
                        "position": {
                            "x": -0.429808348,
                            "y": 1.31263566,
                            "z": 0.256055981
                        },
                        "rotation": {
                            "x": -0.187532,
                            "y": -0.778638244,
                            "z": 0.3530309,
                            "w": -0.483656347
                        }
                    },
                    "leftIndexMedial": {
                        "position": {
                            "x": -0.4577492,
                            "y": 1.2826277,
                            "z": 0.272302121
                        },
                        "rotation": {
                            "x": 0.0461210161,
                            "y": 0.8486927,
                            "z": -0.2129828,
                            "w": 0.481905043
                        }
                    },
                    "leftIndexDistal": {
                        "position": {
                            "x": -0.465443224,
                            "y": 1.2580713,
                            "z": 0.280904979
                        },
                        "rotation": {
                            "x": -0.0195571482,
                            "y": 0.869715631,
                            "z": -0.09610229,
                            "w": 0.483711779
                        }
                    },
                    "leftIndexTip": {
                        "position": {
                            "x": -0.467011422,
                            "y": 1.23199189,
                            "z": 0.285853028
                        },
                        "rotation": {
                            "x": -0.0195574015,
                            "y": 0.8697148,
                            "z": -0.09610258,
                            "w": 0.4837132
                        }
                    },
                    "leftMiddleProximal": {
                        "position": {
                            "x": -0.4374044,
                            "y": 1.29893577,
                            "z": 0.239263624
                        },
                        "rotation": {
                            "x": -0.136957735,
                            "y": -0.579864264,
                            "z": 0.454839379,
                            "w": -0.6619072
                        }
                    },
                    "leftMiddleMedial": {
                        "position": {
                            "x": -0.4718582,
                            "y": 1.27409148,
                            "z": 0.2549376
                        },
                        "rotation": {
                            "x": 0.06541129,
                            "y": -0.6900425,
                            "z": 0.271845847,
                            "w": -0.6675799
                        }
                    },
                    "leftMiddleDistal": {
                        "position": {
                            "x": -0.4800015,
                            "y": 1.24889743,
                            "z": 0.268749475
                        },
                        "rotation": {
                            "x": 0.194902211,
                            "y": -0.729922533,
                            "z": 0.131423622,
                            "w": -0.6418367
                        }
                    },
                    "leftMiddleTip": {
                        "position": {
                            "x": -0.476656377,
                            "y": 1.2232064,
                            "z": 0.281517059
                        },
                        "rotation": {
                            "x": 0.194902062,
                            "y": -0.7299225,
                            "z": 0.1314238,
                            "w": -0.641836762
                        }
                    },
                    "leftRingProximal": {
                        "position": {
                            "x": -0.4395538,
                            "y": 1.28303254,
                            "z": 0.2229611
                        },
                        "rotation": {
                            "x": -0.05628557,
                            "y": -0.5129018,
                            "z": 0.580635,
                            "w": -0.6297828
                        }
                    },
                    "leftRingMedial": {
                        "position": {
                            "x": -0.47292462,
                            "y": 1.26952553,
                            "z": 0.245151743
                        },
                        "rotation": {
                            "x": 0.146941319,
                            "y": -0.6696076,
                            "z": 0.371926755,
                            "w": -0.625863135
                        }
                    },
                    "leftRingDistal": {
                        "position": {
                            "x": -0.480254829,
                            "y": 1.25097477,
                            "z": 0.2637533
                        },
                        "rotation": {
                            "x": 0.2809824,
                            "y": -0.7350079,
                            "z": 0.215562746,
                            "w": -0.57822603
                        }
                    },
                    "leftRingTip": {
                        "position": {
                            "x": -0.47590673,
                            "y": 1.23108125,
                            "z": 0.280796528
                        },
                        "rotation": {
                            "x": 0.280982226,
                            "y": -0.7350078,
                            "z": 0.215562969,
                            "w": -0.5782261
                        }
                    },
                    "leftLittleProximal": {
                        "position": {
                            "x": -0.4351511,
                            "y": 1.26854324,
                            "z": 0.207975581
                        },
                        "rotation": {
                            "x": -0.09547127,
                            "y": -0.178685114,
                            "z": 0.688961446,
                            "w": -0.6959088
                        }
                    },
                    "leftLittleMedial": {
                        "position": {
                            "x": -0.469132572,
                            "y": 1.26743317,
                            "z": 0.21185407
                        },
                        "rotation": {
                            "x": 0.232054591,
                            "y": -0.405473948,
                            "z": 0.462311447,
                            "w": -0.7536643
                        }
                    },
                    "leftLittleDistal": {
                        "position": {
                            "x": -0.480074018,
                            "y": 1.25743473,
                            "z": 0.227441862
                        },
                        "rotation": {
                            "x": 0.4446319,
                            "y": -0.524094462,
                            "z": 0.321661353,
                            "w": -0.651277
                        }
                    },
                    "leftLittleTip": {
                        "position": {
                            "x": -0.4790425,
                            "y": 1.2487216,
                            "z": 0.2475183
                        },
                        "rotation": {
                            "x": 0.4446321,
                            "y": -0.524094462,
                            "z": 0.321661234,
                            "w": -0.6512769
                        }
                    },
                    "rightThumbProximal": {
                        "position": {
                            "x": 0.0,
                            "y": 0.0,
                            "z": 0.0
                        },
                        "rotation": {
                            "x": 0.0,
                            "y": 0.0,
                            "z": 0.0,
                            "w": 0.0
                        }
                    },
                    "rightThumbMedial": {
                        "position": {
                            "x": 0.0,
                            "y": 0.0,
                            "z": 0.0
                        },
                        "rotation": {
                            "x": 0.0,
                            "y": 0.0,
                            "z": 0.0,
                            "w": 0.0
                        }
                    },
                    "rightThumbDistal": {
                        "position": {
                            "x": 0.0,
                            "y": 0.0,
                            "z": 0.0
                        },
                        "rotation": {
                            "x": 0.0,
                            "y": 0.0,
                            "z": 0.0,
                            "w": 0.0
                        }
                    },
                    "rightThumbTip": {
                        "position": {
                            "x": 0.0,
                            "y": 0.0,
                            "z": 0.0
                        },
                        "rotation": {
                            "x": 0.0,
                            "y": 0.0,
                            "z": 0.0,
                            "w": 0.0
                        }
                    },
                    "rightIndexProximal": {
                        "position": {
                            "x": 0.0,
                            "y": 0.0,
                            "z": 0.0
                        },
                        "rotation": {
                            "x": 0.0,
                            "y": 0.0,
                            "z": 0.0,
                            "w": 0.0
                        }
                    },
                    "rightIndexMedial": {
                        "position": {
                            "x": 0.0,
                            "y": 0.0,
                            "z": 0.0
                        },
                        "rotation": {
                            "x": 0.0,
                            "y": 0.0,
                            "z": 0.0,
                            "w": 0.0
                        }
                    },
                    "rightIndexDistal": {
                        "position": {
                            "x": 0.0,
                            "y": 0.0,
                            "z": 0.0
                        },
                        "rotation": {
                            "x": 0.0,
                            "y": 0.0,
                            "z": 0.0,
                            "w": 0.0
                        }
                    },
                    "rightIndexTip": {
                        "position": {
                            "x": 0.0,
                            "y": 0.0,
                            "z": 0.0
                        },
                        "rotation": {
                            "x": 0.0,
                            "y": 0.0,
                            "z": 0.0,
                            "w": 0.0
                        }
                    },
                    "rightMiddleProximal": {
                        "position": {
                            "x": 0.0,
                            "y": 0.0,
                            "z": 0.0
                        },
                        "rotation": {
                            "x": 0.0,
                            "y": 0.0,
                            "z": 0.0,
                            "w": 0.0
                        }
                    },
                    "rightMiddleMedial": {
                        "position": {
                            "x": 0.0,
                            "y": 0.0,
                            "z": 0.0
                        },
                        "rotation": {
                            "x": 0.0,
                            "y": 0.0,
                            "z": 0.0,
                            "w": 0.0
                        }
                    },
                    "rightMiddleDistal": {
                        "position": {
                            "x": 0.0,
                            "y": 0.0,
                            "z": 0.0
                        },
                        "rotation": {
                            "x": 0.0,
                            "y": 0.0,
                            "z": 0.0,
                            "w": 0.0
                        }
                    },
                    "rightMiddleTip": {
                        "position": {
                            "x": 0.0,
                            "y": 0.0,
                            "z": 0.0
                        },
                        "rotation": {
                            "x": 0.0,
                            "y": 0.0,
                            "z": 0.0,
                            "w": 0.0
                        }
                    },
                    "rightRingProximal": {
                        "position": {
                            "x": 0.0,
                            "y": 0.0,
                            "z": 0.0
                        },
                        "rotation": {
                            "x": 0.0,
                            "y": 0.0,
                            "z": 0.0,
                            "w": 0.0
                        }
                    },
                    "rightRingMedial": {
                        "position": {
                            "x": 0.0,
                            "y": 0.0,
                            "z": 0.0
                        },
                        "rotation": {
                            "x": 0.0,
                            "y": 0.0,
                            "z": 0.0,
                            "w": 0.0
                        }
                    },
                    "rightRingDistal": {
                        "position": {
                            "x": 0.0,
                            "y": 0.0,
                            "z": 0.0
                        },
                        "rotation": {
                            "x": 0.0,
                            "y": 0.0,
                            "z": 0.0,
                            "w": 0.0
                        }
                    },
                    "rightRingTip": {
                        "position": {
                            "x": 0.0,
                            "y": 0.0,
                            "z": 0.0
                        },
                        "rotation": {
                            "x": 0.0,
                            "y": 0.0,
                            "z": 0.0,
                            "w": 0.0
                        }
                    },
                    "rightLittleProximal": {
                        "position": {
                            "x": 0.0,
                            "y": 0.0,
                            "z": 0.0
                        },
                        "rotation": {
                            "x": 0.0,
                            "y": 0.0,
                            "z": 0.0,
                            "w": 0.0
                        }
                    },
                    "rightLittleMedial": {
                        "position": {
                            "x": 0.0,
                            "y": 0.0,
                            "z": 0.0
                        },
                        "rotation": {
                            "x": 0.0,
                            "y": 0.0,
                            "z": 0.0,
                            "w": 0.0
                        }
                    },
                    "rightLittleDistal": {
                        "position": {
                            "x": 0.0,
                            "y": 0.0,
                            "z": 0.0
                        },
                        "rotation": {
                            "x": 0.0,
                            "y": 0.0,
                            "z": 0.0,
                            "w": 0.0
                        }
                    },
                    "rightLittleTip": {
                        "position": {
                            "x": 0.0,
                            "y": 0.0,
                            "z": 0.0
                        },
                        "rotation": {
                            "x": 0.0,
                            "y": 0.0,
                            "z": 0.0,
                            "w": 0.0
                        }
                    }
                },
                "face": {}
            }
        ],
        "props": []
    }
}